encrypt_config/__init__.py
encrypt_config/cli.py
encrypt_config/configuration.py
encrypt_config/encrypt_config.py
encrypt_config-0.1.6.dist-info/AUTHORS.rst
encrypt_config-0.1.6.dist-info/LICENSE
encrypt_config-0.1.6.dist-info/METADATA
encrypt_config-0.1.6.dist-info/WHEEL
encrypt_config-0.1.6.dist-info/entry_points.txt
encrypt_config-0.1.6.dist-info/top_level.txt
encrypt_config-0.1.6.dist-info/RECORD
