Metadata-Version: 2.1
Name: encrypt-config
Version: 0.1.6
Summary: Encrypt and decrypt information in configuration files.
Home-page: https://github.com/luiscberrocal/encrypt_config
Author: Luis C. Berrocal
Author-email: luis.berrocal.1942@gmail.com
License: Apache Software License 2.0
Keywords: encrypt_config
Platform: UNKNOWN
Classifier: Development Status :: 2 - Pre-Alpha
Classifier: Intended Audience :: Developers
Classifier: License :: OSI Approved :: Apache Software License
Classifier: Natural Language :: English
Classifier: Programming Language :: Python :: 3
Classifier: Programming Language :: Python :: 3.6
Classifier: Programming Language :: Python :: 3.7
Classifier: Programming Language :: Python :: 3.8
Requires-Python: >=3.6
License-File: LICENSE
License-File: AUTHORS.rst
Requires-Dist: cryptography (==3.4.8)
